isops/__init__.py
isops/cli.py
isops/utils/__init__.py
isops/utils/helpers.py
isops/utils/sops.py
isops-0.3.0.dist-info/METADATA
isops-0.3.0.dist-info/WHEEL
isops-0.3.0.dist-info/entry_points.txt
isops-0.3.0.dist-info/licenses/LICENSE
isops-0.3.0.dist-info/RECORD
