Metadata-Version: 2.4
Name: isops
Version: 0.3.0
Summary: Utility to ensure SOPS secrets are encrypterd.
License-File: LICENSE
Keywords: isops,sops,secrets
Author: Lorenzo Maffioli
Author-email: lorenzo.maffioli@gmail.com
Requires-Python: >=3.9,<4.0
Classifier: Programming Language :: Python :: 3
Classifier: Programming Language :: Python :: 3.9
Classifier: Programming Language :: Python :: 3.10
Classifier: Programming Language :: Python :: 3.11
Classifier: Programming Language :: Python :: 3.12
Classifier: Programming Language :: Python :: 3.13
Classifier: Programming Language :: Python :: 3.14
Requires-Dist: click (>=8.1.3,<9.0.0)
Requires-Dist: pathspec (>=0.12.0,<0.13.0)
Requires-Dist: ruamel-yaml (>=0.18.0,<0.19.0)
Requires-Dist: setuptools (>=69.5.1,<70.0.0)
Project-URL: Repository, https://github.com/lorenzophys/isops
